odoo/addons/purchase_line_procurement_group/README.rst
odoo/addons/purchase_line_procurement_group/__init__.py
odoo/addons/purchase_line_procurement_group/__manifest__.py
odoo/addons/purchase_line_procurement_group/i18n/es.po
odoo/addons/purchase_line_procurement_group/i18n/fr.po
odoo/addons/purchase_line_procurement_group/i18n/it.po
odoo/addons/purchase_line_procurement_group/i18n/ja.po
odoo/addons/purchase_line_procurement_group/i18n/purchase_line_procurement_group.pot
odoo/addons/purchase_line_procurement_group/i18n/zh_CN.po
odoo/addons/purchase_line_procurement_group/models/__init__.py
odoo/addons/purchase_line_procurement_group/models/purchase_order_line.py
odoo/addons/purchase_line_procurement_group/models/stock_move.py
odoo/addons/purchase_line_procurement_group/readme/CONTRIBUTORS.md
odoo/addons/purchase_line_procurement_group/readme/CREDITS.md
odoo/addons/purchase_line_procurement_group/readme/DESCRIPTION.md
odoo/addons/purchase_line_procurement_group/static/description/icon.png
odoo/addons/purchase_line_procurement_group/static/description/index.html
odoo/addons/purchase_line_procurement_group/tests/__init__.py
odoo/addons/purchase_line_procurement_group/tests/test_po_line_proc_group.py
odoo/addons/purchase_line_procurement_group/views/purchase.xml
odoo_addon_purchase_line_procurement_group-18.0.1.0.0.2.dist-info/METADATA
odoo_addon_purchase_line_procurement_group-18.0.1.0.0.2.dist-info/WHEEL
odoo_addon_purchase_line_procurement_group-18.0.1.0.0.2.dist-info/top_level.txt
odoo_addon_purchase_line_procurement_group-18.0.1.0.0.2.dist-info/RECORD
